LICENSE
merqube_client_lib/__init__.py
merqube_client_lib/api_client/__init__.py
merqube_client_lib/api_client/base.py
merqube_client_lib/api_client/merqube_client.py
merqube_client_lib/constants.py
merqube_client_lib/exceptions.py
merqube_client_lib/logging.py
merqube_client_lib/mocker.py
merqube_client_lib/py.typed
merqube_client_lib/pydantic_v2_types.py
merqube_client_lib/secapi/__init__.py
merqube_client_lib/session.py
merqube_client_lib/templates/__init__.py
merqube_client_lib/templates/bin/create_index.py
merqube_client_lib/templates/bin/get_example.py
merqube_client_lib/templates/configs.py
merqube_client_lib/templates/equity_baskets/__init__.py
merqube_client_lib/templates/equity_baskets/bin/update_portfolio.py
merqube_client_lib/templates/equity_baskets/creators.py
merqube_client_lib/templates/equity_baskets/level_overrides.csv
merqube_client_lib/templates/equity_baskets/portfolios.csv
merqube_client_lib/templates/options/creators.py
merqube_client_lib/templates/util.py
merqube_client_lib/types/__init__.py
merqube_client_lib/types/secapi.py
merqube_client_lib/util.py
merqube_client_lib-0.23.2.dist-info/LICENSE
merqube_client_lib-0.23.2.dist-info/METADATA
merqube_client_lib-0.23.2.dist-info/WHEEL
merqube_client_lib-0.23.2.dist-info/entry_points.txt
merqube_client_lib-0.23.2.dist-info/RECORD
