Metadata-Version: 2.1
Name: merqube-client-lib
Version: 0.23.2
Summary: MerQube IndexAPI + SecAPI client library
Home-page: https://github.com/merqube/merqube-client-lib
License: Apache-2.0
Author: Merqube
Requires-Python: >=3.10,<4.0
Classifier: License :: OSI Approved :: Apache Software License
Classifier: Programming Language :: Python :: 3
Classifier: Programming Language :: Python :: 3.10
Classifier: Programming Language :: Python :: 3.11
Requires-Dist: Flask (>=2,<3)
Requires-Dist: Flask-Cors (>=3,<4)
Requires-Dist: boto3
Requires-Dist: cachetools (>=5.2.0,<6.0.0)
Requires-Dist: click (>=8,<9)
Requires-Dist: pandas (>=1.3.0,<3.0.0)
Requires-Dist: pandas_market_calendars
Requires-Dist: pydantic (>=2.1.0,<3)
Requires-Dist: requests
